{
    "attention": {
        "sufficiencies @ 0.01": {
            "mean": 0.09346131304567112,
            "std": 0.1919221554330839
        },
        "comprehensiveness @ 0.01": {
            "mean": 0.8376971940561826,
            "std": 0.24049597926079555
        },
        "sufficiencies @ 0.02": {
            "mean": 0.11693917018006383,
            "std": 0.2077612303537112
        },
        "comprehensiveness @ 0.02": {
            "mean": 0.8360467066986979,
            "std": 0.24438694690344032
        },
        "sufficiencies @ 0.05": {
            "mean": 0.18365074311599663,
            "std": 0.2685742111995715
        },
        "comprehensiveness @ 0.05": {
            "mean": 0.8309037892825807,
            "std": 0.25205628190603707
        },
        "sufficiencies @ 0.1": {
            "mean": 0.27175797714951977,
            "std": 0.34195508069185554
        },
        "comprehensiveness @ 0.1": {
            "mean": 0.8585915296267448,
            "std": 0.24058595273132702
        },
        "sufficiencies @ 0.2": {
            "mean": 0.261088838776835,
            "std": 0.3256884142497233
        },
        "comprehensiveness @ 0.2": {
            "mean": 0.9163676415273555,
            "std": 0.15120020675490897
        },
        "sufficiencies @ 0.5": {
            "mean": 0.24317971682965187,
            "std": 0.3130053064310342
        },
        "comprehensiveness @ 0.5": {
            "mean": 0.9067659059187027,
            "std": 0.1601142763150651
        },
        "sufficiencies @ 1.0": {
            "mean": 0.9998654007877893,
            "std": 0.0012193698607238226
        },
        "comprehensiveness @ 1.0": {
            "mean": 0.7771442294137163,
            "std": 0.3390593862906183
        },
        "AOPC - sufficiency": {
            "mean": 0.30999187998364675,
            "std": 0.16787212811324956
        },
        "AOPC - comprehensiveness": {
            "mean": 0.8519309995034258,
            "std": 0.17502707183448019
        }
    },
    "ig": {
        "sufficiencies @ 0.01": {
            "mean": 0.07098444404791082,
            "std": 0.17789172932873945
        },
        "comprehensiveness @ 0.01": {
            "mean": 0.8397002877019705,
            "std": 0.24222262540225356
        },
        "sufficiencies @ 0.02": {
            "mean": 0.08362323462882673,
            "std": 0.19010363283638446
        },
        "comprehensiveness @ 0.02": {
            "mean": 0.8370476461974831,
            "std": 0.24651579168350485
        },
        "sufficiencies @ 0.05": {
            "mean": 0.11302093378625824,
            "std": 0.22067884867255227
        },
        "comprehensiveness @ 0.05": {
            "mean": 0.8321929584380731,
            "std": 0.2520118180709889
        },
        "sufficiencies @ 0.1": {
            "mean": 0.1550345246114239,
            "std": 0.2615886441412597
        },
        "comprehensiveness @ 0.1": {
            "mean": 0.8302275158181947,
            "std": 0.25795025945713723
        },
        "sufficiencies @ 0.2": {
            "mean": 0.1854118337244401,
            "std": 0.2806957078812867
        },
        "comprehensiveness @ 0.2": {
            "mean": 0.8843010643562871,
            "std": 0.20281989174987178
        },
        "sufficiencies @ 0.5": {
            "mean": 0.19528229923437687,
            "std": 0.27460722308997465
        },
        "comprehensiveness @ 0.5": {
            "mean": 0.8934916921258501,
            "std": 0.16985597361430427
        },
        "sufficiencies @ 1.0": {
            "mean": 0.9999827672620727,
            "std": 0.0001524063133426323
        },
        "comprehensiveness @ 1.0": {
            "mean": 0.77683854674492,
            "std": 0.33920430522570105
        },
        "AOPC - sufficiency": {
            "mean": 0.2576200053279013,
            "std": 0.1614180061632528
        },
        "AOPC - comprehensiveness": {
            "mean": 0.841971387340397,
            "std": 0.18205312634661058
        }
    },
    "random": {
        "sufficiencies @ 0.01": {
            "mean": 0.07222746954355104,
            "std": 0.17866240078868556
        },
        "comprehensiveness @ 0.01": {
            "mean": 0.8282181395881504,
            "std": 0.24552756055383815
        },
        "sufficiencies @ 0.02": {
            "mean": 0.08013393730965572,
            "std": 0.18315120927307776
        },
        "comprehensiveness @ 0.02": {
            "mean": 0.8268847722918177,
            "std": 0.24801057078637825
        },
        "sufficiencies @ 0.05": {
            "mean": 0.09569074844957383,
            "std": 0.19583246152781456
        },
        "comprehensiveness @ 0.05": {
            "mean": 0.8192081561843717,
            "std": 0.25444914547213815
        },
        "sufficiencies @ 0.1": {
            "mean": 0.10159398203345538,
            "std": 0.19664065158085334
        },
        "comprehensiveness @ 0.1": {
            "mean": 0.820102712180315,
            "std": 0.254321085132006
        },
        "sufficiencies @ 0.2": {
            "mean": 0.1297521132920176,
            "std": 0.22315399012586132
        },
        "comprehensiveness @ 0.2": {
            "mean": 0.8663433954804586,
            "std": 0.22131936639929112
        },
        "sufficiencies @ 0.5": {
            "mean": 0.14124112431023156,
            "std": 0.21643402649535476
        },
        "comprehensiveness @ 0.5": {
            "mean": 0.8876546312986374,
            "std": 0.17356835078826843
        },
        "sufficiencies @ 1.0": {
            "mean": 0.9999906075464354,
            "std": 8.129573069158519e-05
        },
        "comprehensiveness @ 1.0": {
            "mean": 0.776528436864361,
            "std": 0.339345772023421
        },
        "AOPC - sufficiency": {
            "mean": 0.2315185689264172,
            "std": 0.133359094891274
        },
        "AOPC - comprehensiveness": {
            "mean": 0.8321343205554447,
            "std": 0.18259553669171832
        }
    },
    "deeplift": {
        "sufficiencies @ 0.01": {
            "mean": 0.06689938810589445,
            "std": 0.17500385682537126
        },
        "comprehensiveness @ 0.01": {
            "mean": 0.8352658766787486,
            "std": 0.24559509362883528
        },
        "sufficiencies @ 0.02": {
            "mean": 0.06948977056881148,
            "std": 0.17458148143937932
        },
        "comprehensiveness @ 0.02": {
            "mean": 0.8362697502761932,
            "std": 0.24591042598776322
        },
        "sufficiencies @ 0.05": {
            "mean": 0.08646228363332067,
            "std": 0.18475089478941478
        },
        "comprehensiveness @ 0.05": {
            "mean": 0.8444241939626594,
            "std": 0.2440831147182344
        },
        "sufficiencies @ 0.1": {
            "mean": 0.1047822869909888,
            "std": 0.19983004301853052
        },
        "comprehensiveness @ 0.1": {
            "mean": 0.8531209559410383,
            "std": 0.24047527212196165
        },
        "sufficiencies @ 0.2": {
            "mean": 0.14350110729703414,
            "std": 0.239646472345351
        },
        "comprehensiveness @ 0.2": {
            "mean": 0.9009658116159158,
            "std": 0.19417481633158262
        },
        "sufficiencies @ 0.5": {
            "mean": 0.2932307511663796,
            "std": 0.32200504520678674
        },
        "comprehensiveness @ 0.5": {
            "mean": 0.9285442536503783,
            "std": 0.12398914714807341
        },
        "sufficiencies @ 1.0": {
            "mean": 0.9999934673715892,
            "std": 5.5447015771520794e-05
        },
        "comprehensiveness @ 1.0": {
            "mean": 0.7762198893773441,
            "std": 0.33948773620214096
        },
        "AOPC - sufficiency": {
            "mean": 0.252051293590574,
            "std": 0.151294398776113
        },
        "AOPC - comprehensiveness": {
            "mean": 0.8535443902146111,
            "std": 0.17379565353173346
        }
    },
    "scaled attention": {
        "sufficiencies @ 0.01": {
            "mean": 0.09634849867837628,
            "std": 0.19350041899187023
        },
        "comprehensiveness @ 0.01": {
            "mean": 0.8358917323689484,
            "std": 0.24185932319456727
        },
        "sufficiencies @ 0.02": {
            "mean": 0.12045188724413505,
            "std": 0.2115777778667954
        },
        "comprehensiveness @ 0.02": {
            "mean": 0.8360603522185841,
            "std": 0.2440285358899497
        },
        "sufficiencies @ 0.05": {
            "mean": 0.18629675420976718,
            "std": 0.2685703540074221
        },
        "comprehensiveness @ 0.05": {
            "mean": 0.8276899266828082,
            "std": 0.25252901741046774
        },
        "sufficiencies @ 0.1": {
            "mean": 0.2674144726374038,
            "std": 0.33877270793066067
        },
        "comprehensiveness @ 0.1": {
            "mean": 0.8541490050254942,
            "std": 0.2420323011576467
        },
        "sufficiencies @ 0.2": {
            "mean": 0.26045531853112946,
            "std": 0.3241100388748966
        },
        "comprehensiveness @ 0.2": {
            "mean": 0.9159631434531846,
            "std": 0.1503689855759914
        },
        "sufficiencies @ 0.5": {
            "mean": 0.24346312144567506,
            "std": 0.3132910118941738
        },
        "comprehensiveness @ 0.5": {
            "mean": 0.9052994892531874,
            "std": 0.1603214267905364
        },
        "sufficiencies @ 1.0": {
            "mean": 0.9999949521415592,
            "std": 4.208224970230622e-05
        },
        "comprehensiveness @ 1.0": {
            "mean": 0.7759128898841584,
            "std": 0.3396301778984762
        },
        "AOPC - sufficiency": {
            "mean": 0.31063214355543517,
            "std": 0.16894852805755894
        },
        "AOPC - comprehensiveness": {
            "mean": 0.8501380769837665,
            "std": 0.17645339969833945
        }
    },
    "gradients": {
        "sufficiencies @ 0.01": {
            "mean": 0.07262949838315544,
            "std": 0.1772604703847616
        },
        "comprehensiveness @ 0.01": {
            "mean": 0.824132707039479,
            "std": 0.24767430117870087
        },
        "sufficiencies @ 0.02": {
            "mean": 0.08525645037674492,
            "std": 0.18493672395852725
        },
        "comprehensiveness @ 0.02": {
            "mean": 0.8164620603617844,
            "std": 0.25731133421713687
        },
        "sufficiencies @ 0.05": {
            "mean": 0.11100050847872005,
            "std": 0.21491235851949875
        },
        "comprehensiveness @ 0.05": {
            "mean": 0.8092729266242833,
            "std": 0.26480118833941335
        },
        "sufficiencies @ 0.1": {
            "mean": 0.14539505088668586,
            "std": 0.24737352810468996
        },
        "comprehensiveness @ 0.1": {
            "mean": 0.7955447081972704,
            "std": 0.2799695058084422
        },
        "sufficiencies @ 0.2": {
            "mean": 0.19572673323426162,
            "std": 0.28742367886547826
        },
        "comprehensiveness @ 0.2": {
            "mean": 0.874722997552441,
            "std": 0.2099359901512383
        },
        "sufficiencies @ 0.5": {
            "mean": 0.21125481920707487,
            "std": 0.2928299651881631
        },
        "comprehensiveness @ 0.5": {
            "mean": 0.9064923169806444,
            "std": 0.151411559569467
        },
        "sufficiencies @ 1.0": {
            "mean": 0.9999958632698265,
            "std": 3.391800266523698e-05
        },
        "comprehensiveness @ 1.0": {
            "mean": 0.7756031232922589,
            "std": 0.3397702461575445
        },
        "AOPC - sufficiency": {
            "mean": 0.26017984626235274,
            "std": 0.15056204820629168
        },
        "AOPC - comprehensiveness": {
            "mean": 0.8288901200068801,
            "std": 0.19131243872581044
        }
    }
}