{
    "random": {
        "sufficiencies @ 0.01": {
            "mean": 0.1902453225440972,
            "std": 0.297927775649054
        },
        "comprehensiveness @ 0.01": {
            "mean": 0.03398082704739313,
            "std": 0.1583196469912865
        },
        "sufficiencies @ 0.02": {
            "mean": 0.17430006596692765,
            "std": 0.2781405883928629
        },
        "comprehensiveness @ 0.02": {
            "mean": 0.05074395351417904,
            "std": 0.18636246011900692
        },
        "sufficiencies @ 0.05": {
            "mean": 0.15477651404167758,
            "std": 0.2545627893526642
        },
        "comprehensiveness @ 0.05": {
            "mean": 0.08217523233254861,
            "std": 0.22955846850388315
        },
        "sufficiencies @ 0.1": {
            "mean": 0.13679592048746925,
            "std": 0.235183165439397
        },
        "comprehensiveness @ 0.1": {
            "mean": 0.11944443397959452,
            "std": 0.2749044741469677
        },
        "sufficiencies @ 0.2": {
            "mean": 0.10002367835763047,
            "std": 0.1769012078671811
        },
        "comprehensiveness @ 0.2": {
            "mean": 0.23441790726648704,
            "std": 0.3703123601123025
        },
        "sufficiencies @ 0.5": {
            "mean": 0.1057193425820433,
            "std": 0.16838710594377804
        },
        "comprehensiveness @ 0.5": {
            "mean": 0.8707689895062335,
            "std": 0.21064036448696588
        },
        "sufficiencies @ 1.0": {
            "mean": 0.19577940501081217,
            "std": 0.2748724499033681
        },
        "comprehensiveness @ 1.0": {
            "mean": 0.9251965828436887,
            "std": 0.18229762366948646
        },
        "AOPC - sufficiency": {
            "mean": 0.15109146414152252,
            "std": 0.18027782214810525
        },
        "AOPC - comprehensiveness": {
            "mean": 0.33096113235573205,
            "std": 0.13610825276030425
        }
    },
    "ig": {
        "sufficiencies @ 0.01": {
            "mean": 0.2007077567705633,
            "std": 0.3159786514178718
        },
        "comprehensiveness @ 0.01": {
            "mean": 0.17169814283964133,
            "std": 0.3489437823115102
        },
        "sufficiencies @ 0.02": {
            "mean": 0.18231422823995366,
            "std": 0.2903324588615407
        },
        "comprehensiveness @ 0.02": {
            "mean": 0.19136700915465166,
            "std": 0.3605443006510335
        },
        "sufficiencies @ 0.05": {
            "mean": 0.1483140513974491,
            "std": 0.250666798513221
        },
        "comprehensiveness @ 0.05": {
            "mean": 0.25623109904972613,
            "std": 0.39604934809213516
        },
        "sufficiencies @ 0.1": {
            "mean": 0.14580838449377803,
            "std": 0.2358681411121595
        },
        "comprehensiveness @ 0.1": {
            "mean": 0.32773137127397206,
            "std": 0.4168599684855916
        },
        "sufficiencies @ 0.2": {
            "mean": 0.12246964686242852,
            "std": 0.20295792979933597
        },
        "comprehensiveness @ 0.2": {
            "mean": 0.45351468782214016,
            "std": 0.42990634072054135
        },
        "sufficiencies @ 0.5": {
            "mean": 0.10175683329009912,
            "std": 0.1671557249989597
        },
        "comprehensiveness @ 0.5": {
            "mean": 0.8686684481161936,
            "std": 0.22394245734649362
        },
        "sufficiencies @ 1.0": {
            "mean": 0.19627853042219728,
            "std": 0.27326271842697614
        },
        "comprehensiveness @ 1.0": {
            "mean": 0.9234391177027457,
            "std": 0.18319652986100285
        },
        "AOPC - sufficiency": {
            "mean": 0.1568070616394956,
            "std": 0.18834964170108243
        },
        "AOPC - comprehensiveness": {
            "mean": 0.4560928394227244,
            "std": 0.2392855628290456
        }
    },
    "deeplift": {
        "sufficiencies @ 0.01": {
            "mean": 0.2107411017264743,
            "std": 0.3251208526918139
        },
        "comprehensiveness @ 0.01": {
            "mean": 0.10335652448952252,
            "std": 0.2759925652111087
        },
        "sufficiencies @ 0.02": {
            "mean": 0.19546185329559398,
            "std": 0.30868829500929873
        },
        "comprehensiveness @ 0.02": {
            "mean": 0.143111534938667,
            "std": 0.31289228530616653
        },
        "sufficiencies @ 0.05": {
            "mean": 0.16912774866682115,
            "std": 0.2734417383370585
        },
        "comprehensiveness @ 0.05": {
            "mean": 0.21870832689489042,
            "std": 0.3719944019485772
        },
        "sufficiencies @ 0.1": {
            "mean": 0.16016607438330482,
            "std": 0.26014405048923345
        },
        "comprehensiveness @ 0.1": {
            "mean": 0.29437002208257873,
            "std": 0.39921763379655434
        },
        "sufficiencies @ 0.2": {
            "mean": 0.14744318965566097,
            "std": 0.24192526296650826
        },
        "comprehensiveness @ 0.2": {
            "mean": 0.48339596931471235,
            "std": 0.4421029903304127
        },
        "sufficiencies @ 0.5": {
            "mean": 0.10788952971884275,
            "std": 0.1649759422344423
        },
        "comprehensiveness @ 0.5": {
            "mean": 0.9241735219796605,
            "std": 0.1488768273844721
        },
        "sufficiencies @ 1.0": {
            "mean": 0.19866362677617064,
            "std": 0.27484872283958584
        },
        "comprehensiveness @ 1.0": {
            "mean": 0.918849900717569,
            "std": 0.18673032982464846
        },
        "AOPC - sufficiency": {
            "mean": 0.16992758917469555,
            "std": 0.21170894060415324
        },
        "AOPC - comprehensiveness": {
            "mean": 0.44085225720251436,
            "std": 0.20810592390700994
        }
    },
    "scaled attention": {
        "sufficiencies @ 0.01": {
            "mean": 0.16307982081013625,
            "std": 0.2640239366159161
        },
        "comprehensiveness @ 0.01": {
            "mean": 0.38668475628197796,
            "std": 0.4302938988153868
        },
        "sufficiencies @ 0.02": {
            "mean": 0.16449775744807885,
            "std": 0.2588323455759857
        },
        "comprehensiveness @ 0.02": {
            "mean": 0.4236627327836791,
            "std": 0.43773262595012435
        },
        "sufficiencies @ 0.05": {
            "mean": 0.14823112315758102,
            "std": 0.23999115879251665
        },
        "comprehensiveness @ 0.05": {
            "mean": 0.5221882846715922,
            "std": 0.4321835139615154
        },
        "sufficiencies @ 0.1": {
            "mean": 0.13394407769905728,
            "std": 0.21050058838180355
        },
        "comprehensiveness @ 0.1": {
            "mean": 0.628975666259374,
            "std": 0.40316224167732684
        },
        "sufficiencies @ 0.2": {
            "mean": 0.10892432889731765,
            "std": 0.18465877051361926
        },
        "comprehensiveness @ 0.2": {
            "mean": 0.7386968826694271,
            "std": 0.3545915969562523
        },
        "sufficiencies @ 0.5": {
            "mean": 0.11179834642804391,
            "std": 0.1832572712980346
        },
        "comprehensiveness @ 0.5": {
            "mean": 0.8956363660838169,
            "std": 0.1977408225856724
        },
        "sufficiencies @ 1.0": {
            "mean": 0.19985754713956055,
            "std": 0.2779253470988554
        },
        "comprehensiveness @ 1.0": {
            "mean": 0.9212374020022429,
            "std": 0.18167744621536616
        },
        "AOPC - sufficiency": {
            "mean": 0.1471904287971108,
            "std": 0.1647642321544597
        },
        "AOPC - comprehensiveness": {
            "mean": 0.6452974415360158,
            "std": 0.23160001880776157
        }
    },
    "gradients": {
        "sufficiencies @ 0.01": {
            "mean": 0.2020863541153802,
            "std": 0.3133931677759664
        },
        "comprehensiveness @ 0.01": {
            "mean": 0.12220972032393859,
            "std": 0.2930905421559465
        },
        "sufficiencies @ 0.02": {
            "mean": 0.1822239410885091,
            "std": 0.2874789261819923
        },
        "comprehensiveness @ 0.02": {
            "mean": 0.16324554912264744,
            "std": 0.33896314897779556
        },
        "sufficiencies @ 0.05": {
            "mean": 0.15916593337911022,
            "std": 0.25774135742241616
        },
        "comprehensiveness @ 0.05": {
            "mean": 0.2246068353967688,
            "std": 0.3760154987722799
        },
        "sufficiencies @ 0.1": {
            "mean": 0.14250177765489633,
            "std": 0.23684607141300013
        },
        "comprehensiveness @ 0.1": {
            "mean": 0.30327509030252103,
            "std": 0.4093820082223462
        },
        "sufficiencies @ 0.2": {
            "mean": 0.13329491355551173,
            "std": 0.21623238331328692
        },
        "comprehensiveness @ 0.2": {
            "mean": 0.4480613559281622,
            "std": 0.44068672728957425
        },
        "sufficiencies @ 0.5": {
            "mean": 0.11056035425804096,
            "std": 0.17446789916673663
        },
        "comprehensiveness @ 0.5": {
            "mean": 0.8763055813356823,
            "std": 0.2109424208024681
        },
        "sufficiencies @ 1.0": {
            "mean": 0.19782838712006906,
            "std": 0.2704227513916862
        },
        "comprehensiveness @ 1.0": {
            "mean": 0.9191949053188058,
            "std": 0.18491590922952436
        },
        "AOPC - sufficiency": {
            "mean": 0.16109452302450253,
            "std": 0.19224608969170667
        },
        "AOPC - comprehensiveness": {
            "mean": 0.43669986253264653,
            "std": 0.21494591388758913
        }
    },
    "attention": {
        "sufficiencies @ 0.01": {
            "mean": 0.16530973605137256,
            "std": 0.2649387740503948
        },
        "comprehensiveness @ 0.01": {
            "mean": 0.3921130522738029,
            "std": 0.4328035948835234
        },
        "sufficiencies @ 0.02": {
            "mean": 0.16658083530038287,
            "std": 0.26062177231293376
        },
        "comprehensiveness @ 0.02": {
            "mean": 0.4248779790254271,
            "std": 0.43867787167162825
        },
        "sufficiencies @ 0.05": {
            "mean": 0.14988062095202506,
            "std": 0.240228442208644
        },
        "comprehensiveness @ 0.05": {
            "mean": 0.5224848038322487,
            "std": 0.43283165176189303
        },
        "sufficiencies @ 0.1": {
            "mean": 0.13352580605663428,
            "std": 0.21033320655092627
        },
        "comprehensiveness @ 0.1": {
            "mean": 0.6297959569021879,
            "std": 0.4033398484594176
        },
        "sufficiencies @ 0.2": {
            "mean": 0.10998771470394593,
            "std": 0.1853009783531612
        },
        "comprehensiveness @ 0.2": {
            "mean": 0.7339595444013743,
            "std": 0.3544915629546145
        },
        "sufficiencies @ 0.5": {
            "mean": 0.11260730406824146,
            "std": 0.18389537922088034
        },
        "comprehensiveness @ 0.5": {
            "mean": 0.8957758744758062,
            "std": 0.19746007831255957
        },
        "sufficiencies @ 1.0": {
            "mean": 0.20560071782659675,
            "std": 0.28044724263658405
        },
        "comprehensiveness @ 1.0": {
            "mean": 0.9149021664129559,
            "std": 0.1894742765967617
        },
        "AOPC - sufficiency": {
            "mean": 0.14907039070845698,
            "std": 0.16544309041772176
        },
        "AOPC - comprehensiveness": {
            "mean": 0.6448441967605433,
            "std": 0.23178106235199447
        }
    }
}