{
    "scaled attention": {
        "sufficiencies @ 0.01": {
            "mean": 0.08940853730950164,
            "std": 0.250997305940254
        },
        "comprehensiveness @ 0.01": {
            "mean": 0.13489730226252042,
            "std": 0.27777047024751195
        },
        "sufficiencies @ 0.02": {
            "mean": 0.09953850069645499,
            "std": 0.24621537980016714
        },
        "comprehensiveness @ 0.02": {
            "mean": 0.23478971314909278,
            "std": 0.3530000239680066
        },
        "sufficiencies @ 0.05": {
            "mean": 0.09355758221938158,
            "std": 0.2489288905367199
        },
        "comprehensiveness @ 0.05": {
            "mean": 0.1435515858241392,
            "std": 0.31505564528577756
        },
        "sufficiencies @ 0.1": {
            "mean": 0.09834783005945476,
            "std": 0.24988257272495062
        },
        "comprehensiveness @ 0.1": {
            "mean": 0.1872309834964706,
            "std": 0.35299498264004187
        },
        "sufficiencies @ 0.2": {
            "mean": 0.1152494874916555,
            "std": 0.24760841990442514
        },
        "comprehensiveness @ 0.2": {
            "mean": 0.3331344344754522,
            "std": 0.42311868081147436
        },
        "sufficiencies @ 0.5": {
            "mean": 0.1957814451270913,
            "std": 0.28886545811763265
        },
        "comprehensiveness @ 0.5": {
            "mean": 0.42235407475231546,
            "std": 0.44379122838343676
        },
        "sufficiencies @ 1.0": {
            "mean": 0.3326578118491813,
            "std": 0.3763220867301392
        },
        "comprehensiveness @ 1.0": {
            "mean": 0.5283515400013374,
            "std": 0.45079856993231676
        },
        "AOPC - sufficiency": {
            "mean": 0.1463630278218173,
            "std": 0.19858135453733522
        },
        "AOPC - comprehensiveness": {
            "mean": 0.28347280485161835,
            "std": 0.2775053438917297
        }
    },
    "deeplift": {
        "sufficiencies @ 0.01": {
            "mean": 0.07820412105032142,
            "std": 0.24749001926539546
        },
        "comprehensiveness @ 0.01": {
            "mean": 0.10598339827753869,
            "std": 0.24060516441554522
        },
        "sufficiencies @ 0.02": {
            "mean": 0.07961354180480915,
            "std": 0.2475477002808237
        },
        "comprehensiveness @ 0.02": {
            "mean": 0.14297585935801652,
            "std": 0.2730260521634519
        },
        "sufficiencies @ 0.05": {
            "mean": 0.08342765578972192,
            "std": 0.24783503493175474
        },
        "comprehensiveness @ 0.05": {
            "mean": 0.21925359665301325,
            "std": 0.31720512758782854
        },
        "sufficiencies @ 0.1": {
            "mean": 0.09083031798637456,
            "std": 0.24806481092328236
        },
        "comprehensiveness @ 0.1": {
            "mean": 0.3247997509250001,
            "std": 0.353938214431945
        },
        "sufficiencies @ 0.2": {
            "mean": 0.12069745511727425,
            "std": 0.25288281560743825
        },
        "comprehensiveness @ 0.2": {
            "mean": 0.6102491570486028,
            "std": 0.3482163226016813
        },
        "sufficiencies @ 0.5": {
            "mean": 0.34897909353072043,
            "std": 0.3758204715650741
        },
        "comprehensiveness @ 0.5": {
            "mean": 0.65528703054066,
            "std": 0.3522360256408391
        },
        "sufficiencies @ 1.0": {
            "mean": 0.41970420662794555,
            "std": 0.4069644437761873
        },
        "comprehensiveness @ 1.0": {
            "mean": 0.7844887879352499,
            "std": 0.2798946765626094
        },
        "AOPC - sufficiency": {
            "mean": 0.17449377027245247,
            "std": 0.18634154313570653
        },
        "AOPC - comprehensiveness": {
            "mean": 0.4061482258197258,
            "std": 0.20353897353624725
        }
    },
    "random": {
        "sufficiencies @ 0.01": {
            "mean": 0.08133285872129965,
            "std": 0.2469370906261388
        },
        "comprehensiveness @ 0.01": {
            "mean": 0.09650324080706373,
            "std": 0.22844055942123245
        },
        "sufficiencies @ 0.02": {
            "mean": 0.08294291715021149,
            "std": 0.24716914120474756
        },
        "comprehensiveness @ 0.02": {
            "mean": 0.12794115004665302,
            "std": 0.254581457183638
        },
        "sufficiencies @ 0.05": {
            "mean": 0.08815967217947743,
            "std": 0.24859450395224986
        },
        "comprehensiveness @ 0.05": {
            "mean": 0.19253938920652408,
            "std": 0.29056392622249616
        },
        "sufficiencies @ 0.1": {
            "mean": 0.0904802994264618,
            "std": 0.24857961729969819
        },
        "comprehensiveness @ 0.1": {
            "mean": 0.28704506387249434,
            "std": 0.32948008740486956
        },
        "sufficiencies @ 0.2": {
            "mean": 0.09312915970878236,
            "std": 0.23000036215937258
        },
        "comprehensiveness @ 0.2": {
            "mean": 0.5728963508718179,
            "std": 0.34993352633259234
        },
        "sufficiencies @ 0.5": {
            "mean": 0.3602929376130984,
            "std": 0.3807862146300996
        },
        "comprehensiveness @ 0.5": {
            "mean": 0.6601561105448392,
            "std": 0.35393171682600455
        },
        "sufficiencies @ 1.0": {
            "mean": 0.3814707577755135,
            "std": 0.377983258325523
        },
        "comprehensiveness @ 1.0": {
            "mean": 0.7241396223353993,
            "std": 0.34191463861512367
        },
        "AOPC - sufficiency": {
            "mean": 0.1682583717964064,
            "std": 0.17637969359884623
        },
        "AOPC - comprehensiveness": {
            "mean": 0.3801744182406845,
            "std": 0.19216982098941338
        }
    },
    "attention": {
        "sufficiencies @ 0.01": {
            "mean": 0.09999467199027322,
            "std": 0.2518883955337901
        },
        "comprehensiveness @ 0.01": {
            "mean": 0.13396882800416307,
            "std": 0.2753286215950521
        },
        "sufficiencies @ 0.02": {
            "mean": 0.103634209609609,
            "std": 0.25233614978295893
        },
        "comprehensiveness @ 0.02": {
            "mean": 0.20584766553442033,
            "std": 0.32209608116948
        },
        "sufficiencies @ 0.05": {
            "mean": 0.10578528378021643,
            "std": 0.25163317982934835
        },
        "comprehensiveness @ 0.05": {
            "mean": 0.3045563751485235,
            "std": 0.36210523967768193
        },
        "sufficiencies @ 0.1": {
            "mean": 0.10535200467151193,
            "std": 0.23799620208059635
        },
        "comprehensiveness @ 0.1": {
            "mean": 0.408313157947841,
            "std": 0.38804251105633486
        },
        "sufficiencies @ 0.2": {
            "mean": 0.12351887905153237,
            "std": 0.23717423403782453
        },
        "comprehensiveness @ 0.2": {
            "mean": 0.5412340777240228,
            "std": 0.40551612542002624
        },
        "sufficiencies @ 0.5": {
            "mean": 0.21970522828514505,
            "std": 0.3017561152365563
        },
        "comprehensiveness @ 0.5": {
            "mean": 0.5654013080916142,
            "std": 0.4260992167083744
        },
        "sufficiencies @ 1.0": {
            "mean": 0.32588574180450447,
            "std": 0.37065677618346826
        },
        "comprehensiveness @ 1.0": {
            "mean": 0.6627411844870967,
            "std": 0.40842190390913075
        },
        "AOPC - sufficiency": {
            "mean": 0.15483943131325606,
            "std": 0.18448720590079085
        },
        "AOPC - comprehensiveness": {
            "mean": 0.40315179956252595,
            "std": 0.28446146116825277
        }
    },
    "ig": {
        "sufficiencies @ 0.01": {
            "mean": 0.09235806687909759,
            "std": 0.24665287237408295
        },
        "comprehensiveness @ 0.01": {
            "mean": 0.14151071828960066,
            "std": 0.29265932004198614
        },
        "sufficiencies @ 0.02": {
            "mean": 0.09369454246499513,
            "std": 0.24698092878538333
        },
        "comprehensiveness @ 0.02": {
            "mean": 0.1791861773275214,
            "std": 0.31756312402355286
        },
        "sufficiencies @ 0.05": {
            "mean": 0.09595238329591198,
            "std": 0.2455264345199613
        },
        "comprehensiveness @ 0.05": {
            "mean": 0.24449176808893353,
            "std": 0.34451809082532675
        },
        "sufficiencies @ 0.1": {
            "mean": 0.10654181720578591,
            "std": 0.24685247209839334
        },
        "comprehensiveness @ 0.1": {
            "mean": 0.3591417727597376,
            "std": 0.37263726746578235
        },
        "sufficiencies @ 0.2": {
            "mean": 0.12579672227727398,
            "std": 0.24181796231407185
        },
        "comprehensiveness @ 0.2": {
            "mean": 0.6459189698894569,
            "std": 0.3415285171008517
        },
        "sufficiencies @ 0.5": {
            "mean": 0.35837463619486526,
            "std": 0.37931851609176476
        },
        "comprehensiveness @ 0.5": {
            "mean": 0.6533762370376556,
            "std": 0.3583041437116105
        },
        "sufficiencies @ 1.0": {
            "mean": 0.38965803819999867,
            "std": 0.3839229590505339
        },
        "comprehensiveness @ 1.0": {
            "mean": 0.7400465698152899,
            "std": 0.32296374482602197
        },
        "AOPC - sufficiency": {
            "mean": 0.1803394580739898,
            "std": 0.17346569295097156
        },
        "AOPC - comprehensiveness": {
            "mean": 0.42338174474402795,
            "std": 0.22572379258926564
        }
    },
    "gradients": {
        "sufficiencies @ 0.01": {
            "mean": 0.10238232178396632,
            "std": 0.24928155145411487
        },
        "comprehensiveness @ 0.01": {
            "mean": 0.15523388194210713,
            "std": 0.3085920598084043
        },
        "sufficiencies @ 0.02": {
            "mean": 0.10447642200343404,
            "std": 0.25043029397672945
        },
        "comprehensiveness @ 0.02": {
            "mean": 0.19457096721282582,
            "std": 0.33327728151974323
        },
        "sufficiencies @ 0.05": {
            "mean": 0.10948231972735634,
            "std": 0.24811848454684937
        },
        "comprehensiveness @ 0.05": {
            "mean": 0.2620989154901154,
            "std": 0.3563193400937539
        },
        "sufficiencies @ 0.1": {
            "mean": 0.11914028346357462,
            "std": 0.24692063596579644
        },
        "comprehensiveness @ 0.1": {
            "mean": 0.3573926730133578,
            "std": 0.37611999340692087
        },
        "sufficiencies @ 0.2": {
            "mean": 0.13354474934779126,
            "std": 0.2353732986788216
        },
        "comprehensiveness @ 0.2": {
            "mean": 0.6088448095313376,
            "std": 0.3550793306208498
        },
        "sufficiencies @ 0.5": {
            "mean": 0.3425903660308957,
            "std": 0.3678322320449468
        },
        "comprehensiveness @ 0.5": {
            "mean": 0.62983147442847,
            "std": 0.375672272610626
        },
        "sufficiencies @ 1.0": {
            "mean": 0.44021142672002395,
            "std": 0.4335994319755134
        },
        "comprehensiveness @ 1.0": {
            "mean": 0.8488893749837776,
            "std": 0.22265354447517383
        },
        "AOPC - sufficiency": {
            "mean": 0.1931182698681489,
            "std": 0.17029308556709793
        },
        "AOPC - comprehensiveness": {
            "mean": 0.4366945852288559,
            "std": 0.2278683619246103
        }
    }
}