{
    "ig": {
        "sufficiencies @ 1.0": {
            "mean": 0.1577713874409748,
            "std": 0.2548227002692813
        },
        "comprehensiveness @ 1.0": {
            "mean": 0.8788344027819852,
            "std": 0.23543715312559751
        },
        "AOPC - sufficiency": {
            "mean": 0.15287943750547978,
            "std": 0.22002409087484054
        },
        "AOPC - comprehensiveness": {
            "mean": 0.8819783860416518,
            "std": 0.23382130927548775
        }
    },
    "random": {
        "sufficiencies @ 1.0": {
            "mean": 0.36915622390725406,
            "std": 0.37491173665558575
        },
        "comprehensiveness @ 1.0": {
            "mean": 0.8883706975247133,
            "std": 0.2354429397662444
        },
        "AOPC - sufficiency": {
            "mean": 0.38081088783587197,
            "std": 0.3495392378976594
        },
        "AOPC - comprehensiveness": {
            "mean": 0.8776907683039252,
            "std": 0.2316494036253375
        }
    },
    "attention": {
        "sufficiencies @ 1.0": {
            "mean": 0.12860443094318902,
            "std": 0.21996468207518458
        },
        "comprehensiveness @ 1.0": {
            "mean": 0.882244607918691,
            "std": 0.2366906327488668
        },
        "AOPC - sufficiency": {
            "mean": 0.1420320666595288,
            "std": 0.21588313441506485
        },
        "AOPC - comprehensiveness": {
            "mean": 0.877430498061618,
            "std": 0.23562228637426974
        }
    },
    "deeplift": {
        "sufficiencies @ 1.0": {
            "mean": 0.1499537465264589,
            "std": 0.2330549056483039
        },
        "comprehensiveness @ 1.0": {
            "mean": 0.8679211264835162,
            "std": 0.2572386882440042
        },
        "AOPC - sufficiency": {
            "mean": 0.14813357831861348,
            "std": 0.20740071723047548
        },
        "AOPC - comprehensiveness": {
            "mean": 0.8677403426743192,
            "std": 0.24501541811361657
        }
    },
    "scaled attention": {
        "sufficiencies @ 1.0": {
            "mean": 0.20504819372697533,
            "std": 0.2838975058134088
        },
        "comprehensiveness @ 1.0": {
            "mean": 0.8633030635299853,
            "std": 0.260386246033602
        },
        "AOPC - sufficiency": {
            "mean": 0.19491168879021917,
            "std": 0.27396781807601767
        },
        "AOPC - comprehensiveness": {
            "mean": 0.8627809731351344,
            "std": 0.25993870795053853
        }
    },
    "gradients": {
        "sufficiencies @ 1.0": {
            "mean": 0.1878400268713701,
            "std": 0.28601486392839554
        },
        "comprehensiveness @ 1.0": {
            "mean": 0.8776679791436175,
            "std": 0.2376937630656615
        },
        "AOPC - sufficiency": {
            "mean": 0.16703176002518674,
            "std": 0.2204517979409428
        },
        "AOPC - comprehensiveness": {
            "mean": 0.8743993749554105,
            "std": 0.23609238232575794
        }
    }
}