{
    "scaled attention": {
        "sufficiencies @ 0.01": {
            "mean": 0.09773022529818641,
            "std": 0.2795318583041346
        },
        "comprehensiveness @ 0.01": {
            "mean": 0.06561325002543601,
            "std": 0.23519445940412181
        },
        "sufficiencies @ 0.02": {
            "mean": 0.09824807975360927,
            "std": 0.27939074731009966
        },
        "comprehensiveness @ 0.02": {
            "mean": 0.06695766039275702,
            "std": 0.23582525734134127
        },
        "sufficiencies @ 0.05": {
            "mean": 0.09936196309628582,
            "std": 0.27908458410870796
        },
        "comprehensiveness @ 0.05": {
            "mean": 0.13132587524438877,
            "std": 0.31457560052691846
        },
        "sufficiencies @ 0.1": {
            "mean": 0.13990358691773844,
            "std": 0.32134725183061225
        },
        "comprehensiveness @ 0.1": {
            "mean": 0.20599682366575658,
            "std": 0.3892776414074873
        },
        "sufficiencies @ 0.2": {
            "mean": 0.2446992888835696,
            "std": 0.3793745233997128
        },
        "comprehensiveness @ 0.2": {
            "mean": 0.29946364784924345,
            "std": 0.42059274600516244
        },
        "sufficiencies @ 0.5": {
            "mean": 0.802679569539416,
            "std": 0.3365322453173119
        },
        "comprehensiveness @ 0.5": {
            "mean": 0.7508529431417619,
            "std": 0.3978664114085901
        },
        "sufficiencies @ 1.0": {
            "mean": 1.0,
            "std": 0.0
        },
        "comprehensiveness @ 1.0": {
            "mean": 0.903618802417734,
            "std": 0.2798671941164974
        },
        "AOPC - sufficiency": {
            "mean": 0.35466038764125785,
            "std": 0.21044931270639786
        },
        "AOPC - comprehensiveness": {
            "mean": 0.3462612861052969,
            "std": 0.1747515769893393
        }
    },
    "deeplift": {
        "sufficiencies @ 0.01": {
            "mean": 0.0960774587895988,
            "std": 0.27990846012718407
        },
        "comprehensiveness @ 0.01": {
            "mean": 0.024475414485791436,
            "std": 0.1392403562008687
        },
        "sufficiencies @ 0.02": {
            "mean": 0.0961230218483867,
            "std": 0.27989581632601473
        },
        "comprehensiveness @ 0.02": {
            "mean": 0.025883149371653237,
            "std": 0.13943705541838897
        },
        "sufficiencies @ 0.05": {
            "mean": 0.08633661010574181,
            "std": 0.26536876417545513
        },
        "comprehensiveness @ 0.05": {
            "mean": 0.06887053609483224,
            "std": 0.23531469125305943
        },
        "sufficiencies @ 0.1": {
            "mean": 0.10041465149769552,
            "std": 0.28221679174544806
        },
        "comprehensiveness @ 0.1": {
            "mean": 0.10566031078277652,
            "std": 0.284902961224543
        },
        "sufficiencies @ 0.2": {
            "mean": 0.1574559477953375,
            "std": 0.34016412869530427
        },
        "comprehensiveness @ 0.2": {
            "mean": 0.19225650623390758,
            "std": 0.3668623111962658
        },
        "sufficiencies @ 0.5": {
            "mean": 0.5162126122459458,
            "std": 0.44593579711206566
        },
        "comprehensiveness @ 0.5": {
            "mean": 0.45312955921612474,
            "std": 0.4462922270731185
        },
        "sufficiencies @ 1.0": {
            "mean": 1.0,
            "std": 0.0
        },
        "comprehensiveness @ 1.0": {
            "mean": 0.903256960144252,
            "std": 0.27976885883993835
        },
        "AOPC - sufficiency": {
            "mean": 0.2932314717546723,
            "std": 0.22417469043631952
        },
        "AOPC - comprehensiveness": {
            "mean": 0.2533617766184768,
            "std": 0.11421688116724563
        }
    },
    "ig": {
        "sufficiencies @ 0.01": {
            "mean": 0.1007139805316257,
            "std": 0.27960650851546015
        },
        "comprehensiveness @ 0.01": {
            "mean": 0.09237053585625903,
            "std": 0.2513535147731718
        },
        "sufficiencies @ 0.02": {
            "mean": 0.10135334450538347,
            "std": 0.2798078146374744
        },
        "comprehensiveness @ 0.02": {
            "mean": 0.10594552169892876,
            "std": 0.2690603420704748
        },
        "sufficiencies @ 0.05": {
            "mean": 0.11045827340157105,
            "std": 0.2924261761037347
        },
        "comprehensiveness @ 0.05": {
            "mean": 0.16967562923829563,
            "std": 0.3443841787524179
        },
        "sufficiencies @ 0.1": {
            "mean": 0.12674270551373684,
            "std": 0.3047114014433264
        },
        "comprehensiveness @ 0.1": {
            "mean": 0.19777399433308335,
            "std": 0.3672129652121203
        },
        "sufficiencies @ 0.2": {
            "mean": 0.16284144246382706,
            "std": 0.34046735039051074
        },
        "comprehensiveness @ 0.2": {
            "mean": 0.2630746573325678,
            "std": 0.40865939654195105
        },
        "sufficiencies @ 0.5": {
            "mean": 0.6826756946432272,
            "std": 0.40829896830477647
        },
        "comprehensiveness @ 0.5": {
            "mean": 0.539606461750123,
            "std": 0.46676637098005225
        },
        "sufficiencies @ 1.0": {
            "mean": 1.0,
            "std": 0.0
        },
        "comprehensiveness @ 1.0": {
            "mean": 0.9028956904169064,
            "std": 0.27967117071315256
        },
        "AOPC - sufficiency": {
            "mean": 0.3263979201513388,
            "std": 0.22531535513264278
        },
        "AOPC - comprehensiveness": {
            "mean": 0.32447749866088055,
            "std": 0.20052609638709432
        }
    },
    "gradients": {
        "sufficiencies @ 0.01": {
            "mean": 0.09662795322023117,
            "std": 0.27495132687759233
        },
        "comprehensiveness @ 0.01": {
            "mean": 0.049841934313403835,
            "std": 0.20649161467584232
        },
        "sufficiencies @ 0.02": {
            "mean": 0.0894819729310158,
            "std": 0.2646304137025025
        },
        "comprehensiveness @ 0.02": {
            "mean": 0.05917190299272707,
            "std": 0.225348081204678
        },
        "sufficiencies @ 0.05": {
            "mean": 0.10011181160959085,
            "std": 0.27888059870504883
        },
        "comprehensiveness @ 0.05": {
            "mean": 0.0686690459107872,
            "std": 0.23522288780330156
        },
        "sufficiencies @ 0.1": {
            "mean": 0.09153797177734149,
            "std": 0.2641813952609263
        },
        "comprehensiveness @ 0.1": {
            "mean": 0.10937992474502309,
            "std": 0.28818542770150263
        },
        "sufficiencies @ 0.2": {
            "mean": 0.11266444311548592,
            "std": 0.28410000336466285
        },
        "comprehensiveness @ 0.2": {
            "mean": 0.16563873844973442,
            "std": 0.3300899573924261
        },
        "sufficiencies @ 0.5": {
            "mean": 0.5876747187700916,
            "std": 0.42900584596616137
        },
        "comprehensiveness @ 0.5": {
            "mean": 0.4104602661175624,
            "std": 0.442497027613897
        },
        "sufficiencies @ 1.0": {
            "mean": 1.0,
            "std": 0.0
        },
        "comprehensiveness @ 1.0": {
            "mean": 0.9025349917921437,
            "std": 0.27957412725511027
        },
        "AOPC - sufficiency": {
            "mean": 0.29687126734625097,
            "std": 0.19898547381308668
        },
        "AOPC - comprehensiveness": {
            "mean": 0.25224240061734027,
            "std": 0.17364564157558912
        }
    },
    "attention": {
        "sufficiencies @ 0.01": {
            "mean": 0.10498717112413689,
            "std": 0.28323673313616765
        },
        "comprehensiveness @ 0.01": {
            "mean": 0.0520192188750798,
            "std": 0.20333225410805844
        },
        "sufficiencies @ 0.02": {
            "mean": 0.10562891331264886,
            "std": 0.2833114141498718
        },
        "comprehensiveness @ 0.02": {
            "mean": 0.06041784717773641,
            "std": 0.2151869168295246
        },
        "sufficiencies @ 0.05": {
            "mean": 0.10447476254858756,
            "std": 0.27979918939500403
        },
        "comprehensiveness @ 0.05": {
            "mean": 0.11987599615972096,
            "std": 0.29913625177144754
        },
        "sufficiencies @ 0.1": {
            "mean": 0.14262250326370904,
            "std": 0.3209613972903227
        },
        "comprehensiveness @ 0.1": {
            "mean": 0.20252466149857837,
            "std": 0.38632495405534817
        },
        "sufficiencies @ 0.2": {
            "mean": 0.24910889905228928,
            "std": 0.3790842697197107
        },
        "comprehensiveness @ 0.2": {
            "mean": 0.2956984857035448,
            "std": 0.41679288866420405
        },
        "sufficiencies @ 0.5": {
            "mean": 0.8078212518257418,
            "std": 0.3324506129398467
        },
        "comprehensiveness @ 0.5": {
            "mean": 0.7395486757545688,
            "std": 0.3965702686545793
        },
        "sufficiencies @ 1.0": {
            "mean": 1.0,
            "std": 0.0
        },
        "comprehensiveness @ 1.0": {
            "mean": 0.9021735395383926,
            "std": 0.27947726296201486
        },
        "AOPC - sufficiency": {
            "mean": 0.35923478587530205,
            "std": 0.21298300481254717
        },
        "AOPC - comprehensiveness": {
            "mean": 0.3388940606725174,
            "std": 0.17217843876553124
        }
    },
    "random": {
        "sufficiencies @ 0.01": {
            "mean": 0.10819631120352981,
            "std": 0.29275310972688595
        },
        "comprehensiveness @ 0.01": {
            "mean": 0.04569283082602767,
            "std": 0.18455155436230308
        },
        "sufficiencies @ 0.02": {
            "mean": 0.10822457524515346,
            "std": 0.292746143815105
        },
        "comprehensiveness @ 0.02": {
            "mean": 0.04726323751876202,
            "std": 0.18464755415402237
        },
        "sufficiencies @ 0.05": {
            "mean": 0.11094915686094524,
            "std": 0.29262137855911685
        },
        "comprehensiveness @ 0.05": {
            "mean": 0.0775722156721386,
            "std": 0.23843156641750213
        },
        "sufficiencies @ 0.1": {
            "mean": 0.1360549275222606,
            "std": 0.3112931940368784
        },
        "comprehensiveness @ 0.1": {
            "mean": 0.06977398632656717,
            "std": 0.21953896423062047
        },
        "sufficiencies @ 0.2": {
            "mean": 0.20278833430703513,
            "std": 0.3565285084782134
        },
        "comprehensiveness @ 0.2": {
            "mean": 0.10475546714628588,
            "std": 0.26560561593585524
        },
        "sufficiencies @ 0.5": {
            "mean": 0.6066498804405515,
            "std": 0.4323347893363752
        },
        "comprehensiveness @ 0.5": {
            "mean": 0.4810671937558678,
            "std": 0.4437047941530252
        },
        "sufficiencies @ 1.0": {
            "mean": 1.0,
            "std": 0.0
        },
        "comprehensiveness @ 1.0": {
            "mean": 0.9018002698972528,
            "std": 0.27937670199384335
        },
        "AOPC - sufficiency": {
            "mean": 0.3246947407970679,
            "std": 0.2253515304141105
        },
        "AOPC - comprehensiveness": {
            "mean": 0.2468464573061289,
            "std": 0.1277173650721108
        }
    }
}