{
    "ig": {
        "sufficiencies @ 0.01": {
            "mean": 0.17346161876491137,
            "std": 0.34811551703152194
        },
        "comprehensiveness @ 0.01": {
            "mean": 0.06139390807630403,
            "std": 0.2183735659715326
        },
        "sufficiencies @ 0.02": {
            "mean": 0.1762515899691903,
            "std": 0.3438260078016324
        },
        "comprehensiveness @ 0.02": {
            "mean": 0.06948335592735634,
            "std": 0.22918152012033266
        },
        "sufficiencies @ 0.05": {
            "mean": 0.19731975688770217,
            "std": 0.3662334891997585
        },
        "comprehensiveness @ 0.05": {
            "mean": 0.11193435577436757,
            "std": 0.29192699323064014
        },
        "sufficiencies @ 0.1": {
            "mean": 0.2072191370572626,
            "std": 0.3729565055353661
        },
        "comprehensiveness @ 0.1": {
            "mean": 0.13351436282895404,
            "std": 0.3103036522610669
        },
        "sufficiencies @ 0.2": {
            "mean": 0.24282931329984916,
            "std": 0.38316294677220436
        },
        "comprehensiveness @ 0.2": {
            "mean": 0.18644474853849347,
            "std": 0.3630822191035125
        },
        "sufficiencies @ 0.5": {
            "mean": 0.6338858742455348,
            "std": 0.415240532786429
        },
        "comprehensiveness @ 0.5": {
            "mean": 0.4259026855328286,
            "std": 0.45121114129250556
        },
        "sufficiencies @ 1.0": {
            "mean": 0.8701707140788174,
            "std": 0.3132891953613278
        },
        "comprehensiveness @ 1.0": {
            "mean": 0.7810669215278794,
            "std": 0.21829584455194911
        },
        "AOPC - sufficiency": {
            "mean": 0.35730542918618113,
            "std": 0.25827738202373907
        },
        "AOPC - comprehensiveness": {
            "mean": 0.2528200483151691,
            "std": 0.2173170560921956
        }
    },
    "gradients": {
        "sufficiencies @ 0.01": {
            "mean": 0.15119362614027615,
            "std": 0.322194256022547
        },
        "comprehensiveness @ 0.01": {
            "mean": 0.04627179554854673,
            "std": 0.19528358329220424
        },
        "sufficiencies @ 0.02": {
            "mean": 0.17097998670825218,
            "std": 0.3434820579080046
        },
        "comprehensiveness @ 0.02": {
            "mean": 0.04495927657736495,
            "std": 0.19424177565944897
        },
        "sufficiencies @ 0.05": {
            "mean": 0.17279558188494948,
            "std": 0.3426618141817831
        },
        "comprehensiveness @ 0.05": {
            "mean": 0.0646784060062675,
            "std": 0.2311916155764867
        },
        "sufficiencies @ 0.1": {
            "mean": 0.16793723472483776,
            "std": 0.3442653544506767
        },
        "comprehensiveness @ 0.1": {
            "mean": 0.08766208966341799,
            "std": 0.2645340841376005
        },
        "sufficiencies @ 0.2": {
            "mean": 0.18366308602012996,
            "std": 0.36013132390377967
        },
        "comprehensiveness @ 0.2": {
            "mean": 0.10779816541178382,
            "std": 0.2864276013511435
        },
        "sufficiencies @ 0.5": {
            "mean": 0.585417874423372,
            "std": 0.4385816355921153
        },
        "comprehensiveness @ 0.5": {
            "mean": 0.30008606373716007,
            "std": 0.43326774395875467
        },
        "sufficiencies @ 1.0": {
            "mean": 0.8735975448046185,
            "std": 0.31480795318147203
        },
        "comprehensiveness @ 1.0": {
            "mean": 0.7809960951800327,
            "std": 0.2178369410888704
        },
        "AOPC - sufficiency": {
            "mean": 0.32936927638663377,
            "std": 0.2421035867314939
        },
        "AOPC - comprehensiveness": {
            "mean": 0.20463598458922486,
            "std": 0.19448633500239337
        }
    },
    "scaled attention": {
        "sufficiencies @ 0.01": {
            "mean": 0.1820236886418363,
            "std": 0.34712367678280237
        },
        "comprehensiveness @ 0.01": {
            "mean": 0.0537039993905856,
            "std": 0.20524574459235517
        },
        "sufficiencies @ 0.02": {
            "mean": 0.15357219482304796,
            "std": 0.32220184817439546
        },
        "comprehensiveness @ 0.02": {
            "mean": 0.053914236841849976,
            "std": 0.20550103123711969
        },
        "sufficiencies @ 0.05": {
            "mean": 0.16856305741544886,
            "std": 0.34317421658566516
        },
        "comprehensiveness @ 0.05": {
            "mean": 0.09000146303737436,
            "std": 0.2637409851042268
        },
        "sufficiencies @ 0.1": {
            "mean": 0.19866997732643088,
            "std": 0.3566962362618247
        },
        "comprehensiveness @ 0.1": {
            "mean": 0.15463865460269885,
            "std": 0.3325187193563647
        },
        "sufficiencies @ 0.2": {
            "mean": 0.2756071601673665,
            "std": 0.39607996967938336
        },
        "comprehensiveness @ 0.2": {
            "mean": 0.2515669851880828,
            "std": 0.40036040626370895
        },
        "sufficiencies @ 0.5": {
            "mean": 0.8405533401934822,
            "std": 0.31698253388332254
        },
        "comprehensiveness @ 0.5": {
            "mean": 0.5365618541609634,
            "std": 0.4578585797988644
        },
        "sufficiencies @ 1.0": {
            "mean": 0.916802751670894,
            "std": 0.248797957357587
        },
        "comprehensiveness @ 1.0": {
            "mean": 0.7801888554339518,
            "std": 0.21877497693187795
        },
        "AOPC - sufficiency": {
            "mean": 0.3908274528912153,
            "std": 0.22980920772279995
        },
        "AOPC - comprehensiveness": {
            "mean": 0.2743680069507867,
            "std": 0.19376226877940944
        }
    },
    "attention": {
        "sufficiencies @ 0.01": {
            "mean": 0.1869944607070141,
            "std": 0.3487632546850844
        },
        "comprehensiveness @ 0.01": {
            "mean": 0.05362689182148027,
            "std": 0.20478490464018675
        },
        "sufficiencies @ 0.02": {
            "mean": 0.1697429869164779,
            "std": 0.341334362692622
        },
        "comprehensiveness @ 0.02": {
            "mean": 0.05341878066187151,
            "std": 0.20448553279516626
        },
        "sufficiencies @ 0.05": {
            "mean": 0.15951021689204664,
            "std": 0.32825286470548426
        },
        "comprehensiveness @ 0.05": {
            "mean": 0.08978479349564503,
            "std": 0.2633888435764222
        },
        "sufficiencies @ 0.1": {
            "mean": 0.19964180969069759,
            "std": 0.3674717160793173
        },
        "comprehensiveness @ 0.1": {
            "mean": 0.15613220463602115,
            "std": 0.3323713178523317
        },
        "sufficiencies @ 0.2": {
            "mean": 0.3042605368780132,
            "std": 0.3998996443951275
        },
        "comprehensiveness @ 0.2": {
            "mean": 0.2593264127393947,
            "std": 0.4051427603619057
        },
        "sufficiencies @ 0.5": {
            "mean": 0.8017835287680037,
            "std": 0.3554234622548274
        },
        "comprehensiveness @ 0.5": {
            "mean": 0.5514402837914543,
            "std": 0.4555488034975171
        },
        "sufficiencies @ 1.0": {
            "mean": 0.9214829952145597,
            "std": 0.24564187571974655
        },
        "comprehensiveness @ 1.0": {
            "mean": 0.7800123920966986,
            "std": 0.2178632608296218
        },
        "AOPC - sufficiency": {
            "mean": 0.39191664786668745,
            "std": 0.24801036621088943
        },
        "AOPC - comprehensiveness": {
            "mean": 0.27767739417750936,
            "std": 0.19639025510094357
        }
    },
    "random": {
        "sufficiencies @ 0.01": {
            "mean": 0.1697431044432956,
            "std": 0.32698948925659627
        },
        "comprehensiveness @ 0.01": {
            "mean": 0.029632642776840402,
            "std": 0.1537405011515092
        },
        "sufficiencies @ 0.02": {
            "mean": 0.10900248308277746,
            "std": 0.25469600019787986
        },
        "comprehensiveness @ 0.02": {
            "mean": 0.02938820007785642,
            "std": 0.15378844369024297
        },
        "sufficiencies @ 0.05": {
            "mean": 0.16430061075653105,
            "std": 0.3215809623725504
        },
        "comprehensiveness @ 0.05": {
            "mean": 0.045790390078107715,
            "std": 0.182482811163091
        },
        "sufficiencies @ 0.1": {
            "mean": 0.11515195641861252,
            "std": 0.24548245161704643
        },
        "comprehensiveness @ 0.1": {
            "mean": 0.04983843801274612,
            "std": 0.17906497168588617
        },
        "sufficiencies @ 0.2": {
            "mean": 0.1657975047625894,
            "std": 0.3091125822587107
        },
        "comprehensiveness @ 0.2": {
            "mean": 0.09512887572832598,
            "std": 0.2502960230293755
        },
        "sufficiencies @ 0.5": {
            "mean": 0.416552951456738,
            "std": 0.42699296708159645
        },
        "comprehensiveness @ 0.5": {
            "mean": 0.2370292566275798,
            "std": 0.3982394688662952
        },
        "sufficiencies @ 1.0": {
            "mean": 0.7013906845914816,
            "std": 0.4129820207895907
        },
        "comprehensiveness @ 1.0": {
            "mean": 0.7779155712349158,
            "std": 0.21910114678219073
        },
        "AOPC - sufficiency": {
            "mean": 0.2631341850731465,
            "std": 0.1794089181850196
        },
        "AOPC - comprehensiveness": {
            "mean": 0.18067476779091032,
            "std": 0.1506503219458763
        }
    },
    "deeplift": {
        "sufficiencies @ 0.01": {
            "mean": 0.16178732173180985,
            "std": 0.33483907001484786
        },
        "comprehensiveness @ 0.01": {
            "mean": 0.02798940412338196,
            "std": 0.14607387625375312
        },
        "sufficiencies @ 0.02": {
            "mean": 0.18634382487439852,
            "std": 0.3492104696344323
        },
        "comprehensiveness @ 0.02": {
            "mean": 0.025932337903745075,
            "std": 0.14314324970408943
        },
        "sufficiencies @ 0.05": {
            "mean": 0.1631317553214657,
            "std": 0.33291500933478624
        },
        "comprehensiveness @ 0.05": {
            "mean": 0.05655147382929608,
            "std": 0.20474031190919995
        },
        "sufficiencies @ 0.1": {
            "mean": 0.2091449301927709,
            "std": 0.3812015347433618
        },
        "comprehensiveness @ 0.1": {
            "mean": 0.0695958765368059,
            "std": 0.22590733792481008
        },
        "sufficiencies @ 0.2": {
            "mean": 0.2380576773049381,
            "std": 0.39852626906117544
        },
        "comprehensiveness @ 0.2": {
            "mean": 0.13543910419193592,
            "std": 0.32622364572840373
        },
        "sufficiencies @ 0.5": {
            "mean": 0.49317102656006834,
            "std": 0.45450940677283863
        },
        "comprehensiveness @ 0.5": {
            "mean": 0.3993846276296214,
            "std": 0.4611102606881557
        },
        "sufficiencies @ 1.0": {
            "mean": 0.9160118269825553,
            "std": 0.25349920434083656
        },
        "comprehensiveness @ 1.0": {
            "mean": 0.7795834895836827,
            "std": 0.21724264261039214
        },
        "AOPC - sufficiency": {
            "mean": 0.3382354804240011,
            "std": 0.266101772137042
        },
        "AOPC - comprehensiveness": {
            "mean": 0.21349661625692418,
            "std": 0.15425430736370957
        }
    }
}