{
    "ece": 0.1451106149046582,
    "refinement": 0.18684607600347414,
    "bins": {
        "1": {
            "acc": 0.0,
            "conf": 0.0
        },
        "2": {
            "acc": 0.0,
            "conf": 0.0
        },
        "3": {
            "acc": 0.0,
            "conf": 0.0
        },
        "4": {
            "acc": 0.25,
            "conf": 0.3799999952316284
        },
        "5": {
            "acc": 0.248,
            "conf": 0.414000004529953
        },
        "6": {
            "acc": 0.0,
            "conf": 0.5230000019073486
        },
        "7": {
            "acc": 0.0,
            "conf": 0.0
        },
        "8": {
            "acc": 0.0,
            "conf": 0.0
        },
        "9": {
            "acc": 0.0,
            "conf": 0.0
        },
        "10": {
            "acc": 0.0,
            "conf": 0.0
        }
    }
}